[{"id":"0","firstName":"chris","lastName":"scott","email":"chrisscott@gmail.com","password":"password","phone":"555-1234"},{"firstName":"sam","lastName":"scott","email":"chrisscott@gmail.com","password":"password","phone":"555-1234","id":"x7bzXQg"},{"firstName":"Christopher","lastName":"Scott","email":"Chris@getfit.us","phoneNum":"7863737921","password":"rertretretertr","id":"0G3b8k0"},{"email":"test@test.com","password":"$2b$10$uwiQfG6Dpg0ZcXy6OWRTaeBDGSiyfY.wwFeePNp5bplXItvWsytUS","refreshToken":"eyJhbGciOiJIUzI1NiIsInR5cCI6IkpXVCJ9.eyJlbWFpbCI6InRlc3RAdGVzdC5jb20iLCJpYXQiOjE2NTc5MjkwNzgsImV4cCI6MTY1ODAxNTQ3OH0.33Ro-W32W5ype-aK5DgdpZUJTDDde0JCsp3LWvGMT98"}]